{"station":{"id":"41025","name":"Diamond Shoals, NC","lat":35.026,"lng":-75.38,"type":"ndbc"},"observations":[{"t":"2026-04-15 20:10","windDir":230,"windSpeed":25.26992,"windGust":29.1576,"waveHeight":null,"wavePeriod":null,"pressure":1018.1,"airTemp":73.75999999999999,"waterTemp":76.64},{"t":"2026-04-15 20:00","windDir":230,"windSpeed":23.32608,"windGust":29.1576,"waveHeight":null,"wavePeriod":null,"pressure":1018.1,"airTemp":73.58,"waterTemp":76.64},{"t":"2026-04-15 19:50","windDir":230,"windSpeed":23.32608,"windGust":27.21376,"waveHeight":5.577427999999999,"wavePeriod":6,"pressure":1018.2,"airTemp":73.75999999999999,"waterTemp":76.64},{"t":"2026-04-15 19:40","windDir":230,"windSpeed":25.26992,"windGust":29.1576,"waveHeight":null,"wavePeriod":null,"pressure":1018.2,"airTemp":73.58,"waterTemp":76.64},{"t":"2026-04-15 19:30","windDir":240,"windSpeed":25.26992,"windGust":29.1576,"waveHeight":null,"wavePeriod":null,"pressure":1018.4,"airTemp":73.4,"waterTemp":76.64},{"t":"2026-04-15 19:20","windDir":230,"windSpeed":23.32608,"windGust":29.1576,"waveHeight":5.249344000000001,"wavePeriod":6,"pressure":1018.5,"airTemp":73.58,"waterTemp":76.64},{"t":"2026-04-15 19:10","windDir":230,"windSpeed":23.32608,"windGust":29.1576,"waveHeight":null,"wavePeriod":null,"pressure":1018.6,"airTemp":73.58,"waterTemp":76.46},{"t":"2026-04-15 19:00","windDir":240,"windSpeed":23.32608,"windGust":29.1576,"waveHeight":null,"wavePeriod":null,"pressure":1018.7,"airTemp":73.75999999999999,"waterTemp":null},{"t":"2026-04-15 18:50","windDir":240,"windSpeed":23.32608,"windGust":29.1576,"waveHeight":5.249344000000001,"wavePeriod":9,"pressure":1018.7,"airTemp":73.75999999999999,"waterTemp":76.46},{"t":"2026-04-15 18:40","windDir":230,"windSpeed":25.26992,"windGust":27.21376,"waveHeight":5.249344000000001,"wavePeriod":null,"pressure":1018.7,"airTemp":73.75999999999999,"waterTemp":76.46},{"t":"2026-04-15 18:30","windDir":230,"windSpeed":23.32608,"windGust":29.1576,"waveHeight":null,"wavePeriod":null,"pressure":1018.7,"airTemp":73.22,"waterTemp":76.28},{"t":"2026-04-15 18:20","windDir":230,"windSpeed":25.26992,"windGust":29.1576,"waveHeight":5.577427999999999,"wavePeriod":5,"pressure":1018.8,"airTemp":73.4,"waterTemp":76.28},{"t":"2026-04-15 18:10","windDir":230,"windSpeed":23.32608,"windGust":29.1576,"waveHeight":null,"wavePeriod":null,"pressure":1018.8,"airTemp":73.58,"waterTemp":75.92},{"t":"2026-04-15 18:00","windDir":230,"windSpeed":23.32608,"windGust":27.21376,"waveHeight":null,"wavePeriod":null,"pressure":1018.7,"airTemp":73.4,"waterTemp":74.12},{"t":"2026-04-15 17:50","windDir":230,"windSpeed":23.32608,"windGust":27.21376,"waveHeight":5.905512,"wavePeriod":null,"pressure":1019.1,"airTemp":73.22,"waterTemp":74.12},{"t":"2026-04-15 17:40","windDir":230,"windSpeed":23.32608,"windGust":27.21376,"waveHeight":null,"wavePeriod":null,"pressure":1019,"airTemp":73.22,"waterTemp":74.12},{"t":"2026-04-15 17:30","windDir":230,"windSpeed":21.38224,"windGust":27.21376,"waveHeight":null,"wavePeriod":null,"pressure":1019.2,"airTemp":73.22,"waterTemp":74.12},{"t":"2026-04-15 17:20","windDir":230,"windSpeed":23.32608,"windGust":27.21376,"waveHeight":5.249344000000001,"wavePeriod":6,"pressure":1019.3,"airTemp":73.22,"waterTemp":74.12},{"t":"2026-04-15 17:10","windDir":230,"windSpeed":21.38224,"windGust":27.21376,"waveHeight":null,"wavePeriod":null,"pressure":1019.3,"airTemp":73.04,"waterTemp":74.3},{"t":"2026-04-15 17:00","windDir":230,"windSpeed":21.38224,"windGust":25.26992,"waveHeight":null,"wavePeriod":null,"pressure":1019.4,"airTemp":73.22,"waterTemp":74.3},{"t":"2026-04-15 16:50","windDir":230,"windSpeed":21.38224,"windGust":25.26992,"waveHeight":5.249344000000001,"wavePeriod":5,"pressure":1019.6,"airTemp":73.22,"waterTemp":74.3},{"t":"2026-04-15 16:40","windDir":230,"windSpeed":21.38224,"windGust":25.26992,"waveHeight":null,"wavePeriod":null,"pressure":1019.7,"airTemp":73.22,"waterTemp":74.3},{"t":"2026-04-15 16:30","windDir":230,"windSpeed":21.38224,"windGust":25.26992,"waveHeight":null,"wavePeriod":null,"pressure":1019.8,"airTemp":73.04,"waterTemp":74.3},{"t":"2026-04-15 16:20","windDir":230,"windSpeed":21.38224,"windGust":25.26992,"waveHeight":5.249344000000001,"wavePeriod":6,"pressure":1019.9,"airTemp":73.04,"waterTemp":74.48},{"t":"2026-04-15 16:10","windDir":230,"windSpeed":21.38224,"windGust":25.26992,"waveHeight":null,"wavePeriod":null,"pressure":1019.8,"airTemp":72.86,"waterTemp":74.3},{"t":"2026-04-15 16:00","windDir":220,"windSpeed":21.38224,"windGust":27.21376,"waveHeight":null,"wavePeriod":null,"pressure":1019.8,"airTemp":72.68,"waterTemp":74.3},{"t":"2026-04-15 15:50","windDir":230,"windSpeed":21.38224,"windGust":25.26992,"waveHeight":5.249344000000001,"wavePeriod":5,"pressure":1019.9,"airTemp":72.5,"waterTemp":74.48},{"t":"2026-04-15 15:40","windDir":230,"windSpeed":21.38224,"windGust":25.26992,"waveHeight":null,"wavePeriod":null,"pressure":1020.1,"airTemp":72.5,"waterTemp":74.48},{"t":"2026-04-15 15:30","windDir":230,"windSpeed":23.32608,"windGust":27.21376,"waveHeight":null,"wavePeriod":null,"pressure":1020.2,"airTemp":72.14,"waterTemp":74.66},{"t":"2026-04-15 15:20","windDir":230,"windSpeed":21.38224,"windGust":25.26992,"waveHeight":4.92126,"wavePeriod":10,"pressure":1020.3,"airTemp":72.32,"waterTemp":null},{"t":"2026-04-15 15:10","windDir":230,"windSpeed":21.38224,"windGust":25.26992,"waveHeight":4.92126,"wavePeriod":null,"pressure":1020.4,"airTemp":72.14,"waterTemp":74.66},{"t":"2026-04-15 15:00","windDir":230,"windSpeed":21.38224,"windGust":25.26992,"waveHeight":null,"wavePeriod":null,"pressure":1020.4,"airTemp":72.14,"waterTemp":74.84},{"t":"2026-04-15 14:50","windDir":230,"windSpeed":21.38224,"windGust":25.26992,"waveHeight":4.92126,"wavePeriod":5,"pressure":1020.5,"airTemp":71.96,"waterTemp":74.84},{"t":"2026-04-15 14:40","windDir":230,"windSpeed":21.38224,"windGust":27.21376,"waveHeight":null,"wavePeriod":null,"pressure":1020.5,"airTemp":71.96,"waterTemp":74.84},{"t":"2026-04-15 14:30","windDir":230,"windSpeed":21.38224,"windGust":25.26992,"waveHeight":null,"wavePeriod":null,"pressure":1020.5,"airTemp":71.78,"waterTemp":74.84},{"t":"2026-04-15 14:20","windDir":230,"windSpeed":21.38224,"windGust":25.26992,"waveHeight":5.249344000000001,"wavePeriod":5,"pressure":1020.4,"airTemp":71.78,"waterTemp":null},{"t":"2026-04-15 14:10","windDir":230,"windSpeed":21.38224,"windGust":25.26992,"waveHeight":5.249344000000001,"wavePeriod":null,"pressure":1020.4,"airTemp":71.6,"waterTemp":75.02},{"t":"2026-04-15 14:00","windDir":230,"windSpeed":21.38224,"windGust":25.26992,"waveHeight":null,"wavePeriod":null,"pressure":1020.5,"airTemp":71.6,"waterTemp":null},{"t":"2026-04-15 13:50","windDir":230,"windSpeed":21.38224,"windGust":23.32608,"waveHeight":4.593176,"wavePeriod":5,"pressure":1020.4,"airTemp":71.78,"waterTemp":75.2},{"t":"2026-04-15 13:40","windDir":230,"windSpeed":21.38224,"windGust":25.26992,"waveHeight":null,"wavePeriod":null,"pressure":1020.2,"airTemp":71.96,"waterTemp":75.2},{"t":"2026-04-15 13:30","windDir":230,"windSpeed":21.38224,"windGust":25.26992,"waveHeight":null,"wavePeriod":null,"pressure":1020.2,"airTemp":71.96,"waterTemp":75.2},{"t":"2026-04-15 13:20","windDir":240,"windSpeed":21.38224,"windGust":25.26992,"waveHeight":4.92126,"wavePeriod":5,"pressure":1020.3,"airTemp":71.96,"waterTemp":75.2},{"t":"2026-04-15 13:10","windDir":240,"windSpeed":21.38224,"windGust":25.26992,"waveHeight":4.92126,"wavePeriod":null,"pressure":1020.3,"airTemp":71.96,"waterTemp":75.2},{"t":"2026-04-15 13:00","windDir":240,"windSpeed":21.38224,"windGust":25.26992,"waveHeight":null,"wavePeriod":null,"pressure":1020.4,"airTemp":72.14,"waterTemp":75.2},{"t":"2026-04-15 12:50","windDir":240,"windSpeed":23.32608,"windGust":27.21376,"waveHeight":5.249344000000001,"wavePeriod":5,"pressure":1020.4,"airTemp":71.96,"waterTemp":75.2},{"t":"2026-04-15 12:40","windDir":240,"windSpeed":21.38224,"windGust":25.26992,"waveHeight":5.249344000000001,"wavePeriod":null,"pressure":1020.3,"airTemp":72.14,"waterTemp":75.38},{"t":"2026-04-15 12:30","windDir":240,"windSpeed":21.38224,"windGust":25.26992,"waveHeight":null,"wavePeriod":null,"pressure":1020.4,"airTemp":72.14,"waterTemp":75.38},{"t":"2026-04-15 12:20","windDir":240,"windSpeed":23.32608,"windGust":25.26992,"waveHeight":5.249344000000001,"wavePeriod":5,"pressure":1020.4,"airTemp":72.14,"waterTemp":75.56}]}